cxglearner-1.3.2.dist-info/WHEEL
cxglearner-1.3.2.dist-info/top_level.txt
cxglearner-1.3.2.dist-info/RECORD
cxglearner-1.3.2.dist-info/METADATA
cxglearner-1.3.2.dist-info/licenses/LICENSE
app/app.py
scripts/run_pruner.py
scripts/run_metric.py
scripts/run_parser.py
scripts/run_rpt_hyper_fit.py
scripts/run_candidate.py
scripts/run_learner.py
scripts/run_encoder.py
scripts/run_association.py
scripts/run_multi_processor.py
scripts/run_dataset.py
scripts/run_pretrain_ase.py
cxglearner.libs/libgomp-a34b3233.so.1.0.0
cxglearner/downloader.py
cxglearner/version.py
cxglearner/__init__.py
cxglearner/controller.py
cxglearner/encoder/base_encoder.py
cxglearner/encoder/dataset.py
cxglearner/encoder/encoder.py
cxglearner/encoder/__init__.py
cxglearner/encoder/cleaner.py
cxglearner/encoder/tokenizer/hf_tokenizer.py
cxglearner/encoder/tokenizer/tokenizer.py
cxglearner/encoder/tokenizer/__init__.py
cxglearner/config/config.py
cxglearner/config/config_learner.py
cxglearner/config/config_lm.py
cxglearner/config/config_experiment.py
cxglearner/config/config_encoder.py
cxglearner/config/config_parser.py
cxglearner/config/__init__.py
cxglearner/config/config_extractor.py
cxglearner/config/config_check.py
cxglearner/extractor/beam_search.py
cxglearner/extractor/__init__.py
cxglearner/extractor/pruner.py
cxglearner/extractor/candidate.py
cxglearner/learner/metric.py
cxglearner/learner/heu_search.py
cxglearner/learner/__init__.py
cxglearner/learner/learner.py
cxglearner/tools/__init__.py
cxglearner/tools/parsers/__init__.py
cxglearner/tools/parsers/RDRPOSTagger/__init__.py
cxglearner/tools/parsers/RDRPOSTagger/pSCRDRtagger/RDRPOSTagger4Vn.py
cxglearner/tools/parsers/RDRPOSTagger/pSCRDRtagger/RDRPOSTagger.py
cxglearner/tools/parsers/RDRPOSTagger/pSCRDRtagger/ExtRDRPOSTagger.py
cxglearner/tools/parsers/RDRPOSTagger/pSCRDRtagger/__init__.py
cxglearner/tools/parsers/RDRPOSTagger/pSCRDRtagger/RDRPOSTagger4En.py
cxglearner/tools/parsers/RDRPOSTagger/InitialTagger/InitialTagger.py
cxglearner/tools/parsers/RDRPOSTagger/InitialTagger/InitialTagger4Vn.py
cxglearner/tools/parsers/RDRPOSTagger/InitialTagger/__init__.py
